odoo/addons/hr_timesheet_employee_cost_currency/README.rst
odoo/addons/hr_timesheet_employee_cost_currency/__init__.py
odoo/addons/hr_timesheet_employee_cost_currency/__manifest__.py
odoo/addons/hr_timesheet_employee_cost_currency/i18n/es.po
odoo/addons/hr_timesheet_employee_cost_currency/i18n/hr_timesheet_employee_cost_currency.pot
odoo/addons/hr_timesheet_employee_cost_currency/i18n/it.po
odoo/addons/hr_timesheet_employee_cost_currency/models/__init__.py
odoo/addons/hr_timesheet_employee_cost_currency/models/hr_employee.py
odoo/addons/hr_timesheet_employee_cost_currency/readme/CONTRIBUTORS.rst
odoo/addons/hr_timesheet_employee_cost_currency/readme/DESCRIPTION.rst
odoo/addons/hr_timesheet_employee_cost_currency/static/description/icon.png
odoo/addons/hr_timesheet_employee_cost_currency/static/description/index.html
odoo/addons/hr_timesheet_employee_cost_currency/tests/__init__.py
odoo/addons/hr_timesheet_employee_cost_currency/tests/test_hr_timesheet_employee_cost_currency.py
odoo/addons/hr_timesheet_employee_cost_currency/views/hr_employee.xml
odoo12_addon_hr_timesheet_employee_cost_currency-12.0.1.0.0.99.dev11.dist-info/METADATA
odoo12_addon_hr_timesheet_employee_cost_currency-12.0.1.0.0.99.dev11.dist-info/WHEEL
odoo12_addon_hr_timesheet_employee_cost_currency-12.0.1.0.0.99.dev11.dist-info/top_level.txt
odoo12_addon_hr_timesheet_employee_cost_currency-12.0.1.0.0.99.dev11.dist-info/RECORD
